Metadata-Version: 2.1
Name: MorataDePrueba
Version: 1.0.0
Summary: Shit to test how is 
Home-page: https://github.com/Cesuuur/PublishPyCodeTest
Author: César Redondo Urdiales
Author-email: kaluti12@gmail.com
License: UNKNOWN
Keywords: maps location address
Platform: UNKNOWN
Classifier: Development Status :: 4 - Beta
Classifier: Intended Audience :: Developers
Classifier: Topic :: Internet
Classifier: License :: OSI Approved :: MIT License
Classifier: Programming Language :: Python
Classifier: Programming Language :: Python :: 2
Classifier: Programming Language :: Python :: 2.6
Classifier: Programming Language :: Python :: 2.7
Classifier: Programming Language :: Python :: 3
Classifier: Programming Language :: Python :: 3.3
Classifier: Programming Language :: Python :: 3.4
Classifier: Programming Language :: Python :: 3.5
